memoizek/__init__.py
memoizek/memoizek.py
memoizek-0.1.0.dist-info/LICENSE
memoizek-0.1.0.dist-info/METADATA
memoizek-0.1.0.dist-info/WHEEL
memoizek-0.1.0.dist-info/top_level.txt
memoizek-0.1.0.dist-info/RECORD
