Metadata-Version: 2.1
Name: memoizek
Version: 0.1.0
Summary: A simple adjustable memoization tool.
Author-email: Alan Bergsneider <bergsneideralan@gmail.com>
Project-URL: Homepage, https://github.com/alanb43/memoizeK
Project-URL: Bug Tracker, https://github.com/alanb43/memoizeK/issues
Classifier: Programming Language :: Python :: 3
Classifier: License :: OSI Approved :: MIT License
Classifier: Operating System :: OS Independent
Requires-Python: >=3.5
License-File: LICENSE
